LICENSE.txt
MANIFEST.in
README.md
setup.py
isyatirimhisse/FetchFinancials.py
isyatirimhisse/FetchStockData.py
isyatirimhisse/__init__.py
isyatirimhisse.egg-info/PKG-INFO
isyatirimhisse.egg-info/SOURCES.txt
isyatirimhisse.egg-info/dependency_links.txt
isyatirimhisse.egg-info/requires.txt
isyatirimhisse.egg-info/top_level.txt