Metadata-Version: 2.1
Name: isyatirimhisse
Version: 4.0.0
Summary: İş Yatırım'ın web sitesinden veri çekme işlemlerini kolaylaştıran ve isteğe göre özelleştirilebilen bir kütüphane.
Home-page: https://github.com/urazakgul/isyatirimhisse
Author: Uraz Akgül
Author-email: urazdev@gmail.com
License: MIT
Classifier: Programming Language :: Python :: 3
Classifier: License :: OSI Approved :: MIT License
Classifier: Operating System :: OS Independent
Requires-Python: >=3.8
License-File: LICENSE.txt
Requires-Dist: requests
Requires-Dist: pandas
Requires-Dist: numpy
Requires-Dist: openpyxl
